iqapt/__init__.py
iqapt/metric/__init__.py
iqapt/metric/fid.py
iqapt/metric/lpips.py
iqapt/metric/metric.py
iqapt/metric/mse.py
iqapt/metric/psnr.py
iqapt/metric/ssim.py
iqapt/model/__init__.py
iqapt/model/fid/__init__.py
iqapt/model/fid/inceptionV3.py
iqapt/model/fid/preprocess_layer.py
iqapt/model/lpips/__init__.py
iqapt/model/lpips/alex_net.py
iqapt/model/lpips/linear_layer.py
iqapt/model/lpips/scaling_layer.py
iqapt/model/lpips/squeeze_net.py
iqapt/model/lpips/vgg.py
iqapt/utils/__init__.py
iqapt/utils/filter.py
iqapt/utils/image_colorspace.py
iqapt/utils/util_calc.py
iqapt/utils/util_device.py
iqapt/utils/utils.py
iqapt-0.4.0.dist-info/LICENSE
iqapt-0.4.0.dist-info/METADATA
iqapt-0.4.0.dist-info/WHEEL
iqapt-0.4.0.dist-info/top_level.txt
iqapt-0.4.0.dist-info/RECORD
